LICENSE.txt
MANIFEST.in
README.rst
requirements.txt
setup.py
keen/Padding.py
keen/__init__.py
keen/api.py
keen/cached_datasets.py
keen/client.py
keen/direction.py
keen/exceptions.py
keen/persistence_strategies.py
keen/saved_queries.py
keen/scoped_keys.py
keen/utilities.py
keen.egg-info/PKG-INFO
keen.egg-info/SOURCES.txt
keen.egg-info/dependency_links.txt
keen.egg-info/requires.txt
keen.egg-info/top_level.txt